easy_tree/__init__.py
easy_tree/entities.py
easy_tree/logic.py
easy_tree/random_forest.py
easy_tree/tree.py
easy_tree/usecases.py
the_easy_tree-0.2.0.dist-info/LICENSE
the_easy_tree-0.2.0.dist-info/METADATA
the_easy_tree-0.2.0.dist-info/WHEEL
the_easy_tree-0.2.0.dist-info/RECORD
