Metadata-Version: 2.3
Name: the-easy-tree
Version: 0.2.0
Summary: Decision tree and Random Forest algorithms implementation for regression and classification with minimal boilerplate code.
License: MIT
Author: Yury Choi
Author-email: yurytsoy@gmail.com
Requires-Python: >=3.11
Classifier: License :: OSI Approved :: MIT License
Classifier: Programming Language :: Python :: 3
Classifier: Programming Language :: Python :: 3.11
Classifier: Programming Language :: Python :: 3.12
Classifier: Programming Language :: Python :: 3.13
Classifier: Topic :: Scientific/Engineering
Classifier: Topic :: Software Development
Requires-Dist: numpy (>=2.2.4,<3.0.0)
Requires-Dist: orjson (>=3.10.16,<4.0.0)
Requires-Dist: polars (>=1.26.0,<2.0.0)
Project-URL: Repository, https://github.com/yurytsoy/easy-tree
